linkedin_api/__init__.py
linkedin_api/client.py
linkedin_api/cookie_repository.py
linkedin_api/linkedin.py
linkedin_api/settings.py
linkedin_api/utils/__init__.py
linkedin_api/utils/helpers.py
linkedin_api_no_cookie-1.12.dist-info/LICENSE
linkedin_api_no_cookie-1.12.dist-info/METADATA
linkedin_api_no_cookie-1.12.dist-info/WHEEL
linkedin_api_no_cookie-1.12.dist-info/top_level.txt
linkedin_api_no_cookie-1.12.dist-info/RECORD
