Metadata-Version: 2.1
Name: linkedin-api-no-cookie
Version: 1.12
Summary: Python wrapper for the Linkedin API
Home-page: https://github.com/agonzalezreyes/linkedin-api
Author: Alejandrina Gonzalez
Author-email: me@alejandrina.me
License: MIT
Classifier: Programming Language :: Python :: 3
Classifier: License :: OSI Approved :: MIT License
Classifier: Operating System :: OS Independent
License-File: LICENSE
Requires-Dist: requests
Requires-Dist: beautifulsoup4
Requires-Dist: lxml
